{
  "project_info": {
    "project_number": "1007973562225",
    "firebase_url": "https://inventory-management-sys-2bf48.firebaseio.com",
    "project_id": "inventory-management-sys-2bf48",
    "storage_bucket": "inventory-management-sys-2bf48.appspot.com"
  },
  "client": [
    {
      "client_info": {
        "mobilesdk_app_id": "1:1007973562225:android:9aec0dc9acd1775b",
        "android_client_info": {
          "package_name": "com.anirudhv.android.ims"
        }
      },
      "oauth_client": [
        {
          "client_id": "1007973562225-2rnbrs6p0hati5t9rf1chkh91mdislti.apps.googleusercontent.com",
          "client_type": 3
        }
      ],
      "api_key": [
        {
          "current_key": "AIzaSyBrxAkF2m98d4XIVpi2x7n6No5gGk1Gisw"
        }
      ],
      "services": {
        "analytics_service": {
          "status": 1
        },
        "appinvite_service": {
          "status": 1,
          "other_platform_oauth_client": []
        },
        "ads_service": {
          "status": 2
        }
      }
    }
  ],
  "configuration_version": "1"
}